Metadata-Version: 2.1
Name: nanovar
Version: 1.8.2
Summary: Structural variant caller using low-depth long reads
Author-email: CY Tham <chengyong.tham@u.nus.edu>
Project-URL: Homepage, https://github.com/cytham/nanovar
Project-URL: Repository, https://github.com/cytham/nanovar.git
Project-URL: Issues, https://github.com/cytham/nanovar/issues
Project-URL: Changelog, https://github.com/cytham/nanovar/blob/main/CHANGELOG.txt
Keywords: nanovar,structural variant caller,sv,nanopore,long read,low coverage,low depth
Classifier: Operating System :: POSIX :: Linux
Classifier: Programming Language :: Python :: 3.8
Classifier: License :: OSI Approved :: GNU General Public License v3 (GPLv3)
Classifier: Topic :: Scientific/Engineering :: Bio-Informatics
Requires-Python: >=3.8
License-File: LICENSE.txt
Requires-Dist: numpy<2.0.0,>=1.17.3
Requires-Dist: scipy>=1.2.1
Requires-Dist: biopython>=1.82
Requires-Dist: pybedtools>=0.8.2
Requires-Dist: matplotlib>=2.2.3
Requires-Dist: tensorflow-cpu<=2.15.1,>=2.0.0
Requires-Dist: natsort>=6.2.0
Requires-Dist: pysam>=0.15.3
Requires-Dist: bs4>=0.0.2
